magic_ringneck/__init__.py
magic_ringneck/directories.py
magic_ringneck/message.py
magic_ringneck/nestbox.py
magic_ringneck/parakeet.py
magic_ringneck/ringneck.py
magic_ringneck/starter.py
magic_ringneck-1.dist-info/entry_points.txt
magic_ringneck-1.dist-info/WHEEL
magic_ringneck-1.dist-info/METADATA
magic_ringneck-1.dist-info/RECORD
