Metadata-Version: 2.1
Name: magic_ringneck
Version: 1
Summary: Ringneck is a Unix command line tool that caches the output of commands it runs.
Requires-Python: >=3.11
Classifier: Programming Language :: Python :: 3
Classifier: License :: OSI Approved :: Apache Software License
Classifier: Operating System :: OS Independent
Requires-Dist: supervisor == 4.2.5
Requires-Dist: xdg-base-dirs == 6.0
Requires-Dist: retry2 == 0.9.5
Requires-Dist: pylint == 3.1 ; extra == "dev"
Requires-Dist: black == 24.3 ; extra == "dev"
Requires-Dist: mypy == 1.9 ; extra == "dev"
Requires-Dist: types-retry == 0.9 ; extra == "dev"
Requires-Dist: pytest == 8.1 ; extra == "test"
Requires-Dist: pytest-shell-utilities == 1.9 ; extra == "test"
Requires-Dist: hypothesis == 6.99 ; extra == "test"
Project-URL: Homepage, https://github.com/blob79/magic-ringneck
Provides-Extra: dev
Provides-Extra: test
